History.txt
MANIFEST.in
README.rst
To_Do.txt
setup.cfg
setup.py
pyVertProf/__init__.py
pyVertProf/_version.py
pyVertProf/graph.png
pyVertProf/statsfuncs.py
pyVertProf/vertprof.py
pyVertProf.egg-info/PKG-INFO
pyVertProf.egg-info/SOURCES.txt
pyVertProf.egg-info/dependency_links.txt
pyVertProf.egg-info/not-zip-safe
pyVertProf.egg-info/requires.txt
pyVertProf.egg-info/top_level.txt
pyVertProf/test/results_testAFT.txt
pyVertProf/test/results_testAFT2.txt
pyVertProf/test/results_testAFT3.txt
pyVertProf/test/results_testAHe.txt
pyVertProf/test/test.txt
pyVertProf/test/testAFT.txt
pyVertProf/test/testAFT2.txt
pyVertProf/test/testAFT3.txt
pyVertProf/test/testAHe.txt
pyVertProf/test/testBenj.txt