Metadata-Version: 1.1
Name: pyVertProf
Version: 2.0.0
Summary: package that provide tools to perform stats on vertical profils
Home-page: https://github.com/robertxa/pyVertProf
Author: Xavier Robert
Author-email: xavier.robert@univ-grenoble-alpes.fr
License: CCby-nc-sa
Download-URL: https://github.com/robertxa/pyVertProf/archive/master.zip
Platform: UNKNOWN
Classifier: Operating System :: OS Independent
Classifier: Topic :: Scientific/Engineering :: Visualization
